LICENSE
MANIFEST.in
NOTICE
README
pips.py
setup.py
Pylon.egg-info/PKG-INFO
Pylon.egg-info/SOURCES.txt
Pylon.egg-info/dependency_links.txt
Pylon.egg-info/entry_points.txt
Pylon.egg-info/top_level.txt
Pylon.egg-info/zip-safe
doc/pylon.pdf
examples/estimator.py
examples/ipopt_opf.py
examples/load_profile.py
examples/opf.py
examples/pf.py
examples/picloud.py
examples/profile.py
examples/data/PgAC.mtx
examples/data/PgDC.mtx
examples/data/QgAC.mtx
examples/data/bench30.raw
examples/data/case30pwl.m
examples/data/case3bus_P6_6.m
examples/data/case6ww.pkl
examples/data/fAC.mtx
examples/data/fDC.mtx
examples/national_grid/national_grid.py
examples/national_grid/ngt.py
examples/national_grid/pathdata.py
examples/national_grid/placemark.py
examples/national_grid/svg2kml.py
examples/national_grid/tikz.py
examples/pips/cone.py
examples/pips/nlp.py
examples/pips/qp.py
examples/pyreto/auction.py
examples/pyreto/bandit.py
examples/pyreto/discrete.py
examples/pyreto/episodic.py
examples/pyreto/rlopf.py
examples/pyreto/robin.py
examples/pyreto/thesis/common.py
examples/pyreto/thesis/costplot.py
examples/pyreto/thesis/ex5_1.py
examples/pyreto/thesis/ex6_1.py
examples/pyreto/thesis/nash.py
examples/pyreto/thesis/plot.py
pylon/__init__.py
pylon/ac_pf.py
pylon/case.py
pylon/dc_pf.py
pylon/dyn.py
pylon/estimator.py
pylon/generator.py
pylon/ipopf.py
pylon/main.py
pylon/opf.py
pylon/solver.py
pylon/util.py
pylon/io/__init__.py
pylon/io/common.py
pylon/io/dot.py
pylon/io/excel.py
pylon/io/matpower.py
pylon/io/parsing_util.py
pylon/io/pickle.py
pylon/io/psat.py
pylon/io/psse.py
pylon/io/rdf.py
pylon/io/rst.py
pylon/test/__init__.py
pylon/test/acpf_test.py
pylon/test/case_test.py
pylon/test/dcpf_test.py
pylon/test/generator_test.py
pylon/test/opf_model_test.py
pylon/test/opf_test.py
pylon/test/reader_test.py
pylon/test/se_test.py
pylon/test/suite.py
pylon/test/udopf_test.py
pylon/test/data/bench30.m
pylon/test/data/bench30.raw
pylon/test/data/case24_ieee_rts.m
pylon/test/data/case30pwl.m
pylon/test/data/case3bus_P6_6.m
pylon/test/data/case6ww-3.2.m
pylon/test/data/case6ww.m
pylon/test/data/case_ieee30.m
pylon/test/data/d_006_mdl.m
pylon/test/data/ehv3.raw
