Metadata-Version: 1.0
Name: Pylon
Version: 0.4.4
Summary: Port of MATPOWER to Python.
Home-page: http://rwl.github.com/pylon
Author: Richard Lincoln
Author-email: r.w.lincoln@gmail.com
License: Apache License, Version 2.0
Platform: UNKNOWN
